iterators/__init__.py
iterators/timeout_iterator.py
iterators-0.1.0.dist-info/LICENSE
iterators-0.1.0.dist-info/METADATA
iterators-0.1.0.dist-info/WHEEL
iterators-0.1.0.dist-info/top_level.txt
iterators-0.1.0.dist-info/RECORD
