Metadata-Version: 2.1
Name: iterators
Version: 0.1.0
Summary: Iterator utility classes and functions
Home-page: https://github.com/leangaurav/pypi_iterator
Download-URL: https://github.com/leangaurav/pypi_iterator/archive/v_0.1.0.tar.gz
Author: leangaurav
Author-email: leangaurav.me@gmail.com
Keywords: ITERATOR,TIMEOUT,SYNC
Classifier: Programming Language :: Python :: 3
Classifier: License :: OSI Approved :: MIT License
Classifier: Operating System :: OS Independent
Classifier: Topic :: Software Development :: Libraries :: Python Modules
Requires-Python: >=3.6
License-File: LICENSE
